{"getting-started_index.md":"DIAoEC7y","getting-started_installation.md":"CaZyiLF6","getting-started_quick-start.md":"DQ2J8uEv","guide_builder.md":"CqbZI0qN","guide_caching.md":"C8oFtU8d","guide_cancellation.md":"DMFaVWpW","guide_container.md":"D2S7nvLF","guide_groups.md":"CkEI32TV","guide_index.md":"CbatxRrb","guide_issues.md":"CrYBA172","guide_one-of.md":"vjPiDjfu","guide_optional.md":"CI0GTQ14","guide_path-filtering.md":"D4ta0uwx","guide_run-modes.md":"kk8zfCH7","guide_validator.md":"CV3Hb1ZA","index.md":"D-U2iOSj","integrations_index.md":"Dq2qSF9u","integrations_standard-schema.md":"D0OM0eTk","integrations_validator-js.md":"8YsagC5A","integrations_vue.md":"t5k6Dx5a","integrations_vuecs-forms.md":"Ds8akIUC","integrations_zod.md":"BBtS5aAr"}
